OperatingSystemsLectureNotesStanfordCs140/README.md
OperatingSystemsLectureNotesStanfordCs140/__init__.py
OperatingSystemsLectureNotesStanfordCs140/__main__.py
OperatingSystemsLectureNotesStanfordCs140/file.epub
OperatingSystemsLectureNotesStanfordCs140/index.html
OperatingSystemsLectureNotesStanfordCs140/css/__init__.py
OperatingSystemsLectureNotesStanfordCs140/css/annotations.css
OperatingSystemsLectureNotesStanfordCs140/css/main.css
OperatingSystemsLectureNotesStanfordCs140/css/normalize.css
OperatingSystemsLectureNotesStanfordCs140/css/popup.css
OperatingSystemsLectureNotesStanfordCs140/font/__init__.py
OperatingSystemsLectureNotesStanfordCs140/font/fontello.eot
OperatingSystemsLectureNotesStanfordCs140/font/fontello.svg
OperatingSystemsLectureNotesStanfordCs140/font/fontello.ttf
OperatingSystemsLectureNotesStanfordCs140/font/fontello.woff
OperatingSystemsLectureNotesStanfordCs140/img/__init__.py
OperatingSystemsLectureNotesStanfordCs140/img/annotator-glyph-sprite.png
OperatingSystemsLectureNotesStanfordCs140/img/annotator-icon-sprite.png
OperatingSystemsLectureNotesStanfordCs140/img/apple-touch-icon.png
OperatingSystemsLectureNotesStanfordCs140/img/cancelfullscreen.png
OperatingSystemsLectureNotesStanfordCs140/img/close.png
OperatingSystemsLectureNotesStanfordCs140/img/fullscreen.png
OperatingSystemsLectureNotesStanfordCs140/img/loader.gif
OperatingSystemsLectureNotesStanfordCs140/img/menu-icon.png
OperatingSystemsLectureNotesStanfordCs140/img/save.png
OperatingSystemsLectureNotesStanfordCs140/img/saved.png
OperatingSystemsLectureNotesStanfordCs140/img/settings-s.png
OperatingSystemsLectureNotesStanfordCs140/img/settings.png
OperatingSystemsLectureNotesStanfordCs140/img/star.png
OperatingSystemsLectureNotesStanfordCs140/js/__init__.py
OperatingSystemsLectureNotesStanfordCs140/js/epub.js
OperatingSystemsLectureNotesStanfordCs140/js/epub.min.js
OperatingSystemsLectureNotesStanfordCs140/js/epub.min.map
OperatingSystemsLectureNotesStanfordCs140/js/hooks.min.js
operating_systems_lecture_notes_stanford_cs140-2024.3.2.0.dist-info/METADATA
operating_systems_lecture_notes_stanford_cs140-2024.3.2.0.dist-info/WHEEL
operating_systems_lecture_notes_stanford_cs140-2024.3.2.0.dist-info/entry_points.txt
operating_systems_lecture_notes_stanford_cs140-2024.3.2.0.dist-info/top_level.txt
operating_systems_lecture_notes_stanford_cs140-2024.3.2.0.dist-info/RECORD
